command_line.py
corona_info.py
corona_info-1.0.13.dist-info/METADATA
corona_info-1.0.13.dist-info/WHEEL
corona_info-1.0.13.dist-info/entry_points.txt
corona_info-1.0.13.dist-info/top_level.txt
corona_info-1.0.13.dist-info/RECORD
