Metadata-Version: 2.1
Name: corona-info
Version: 1.0.13
Summary: Get faassst information about the corona outbreak, because who likes to google?
Home-page: UNKNOWN
License: UNKNOWN
Platform: UNKNOWN
Requires-Dist: requests
Requires-Dist: bs4
Requires-Dist: pandas
Requires-Dist: tabulate
